mach2-1.0.2.dist-info/METADATA
mach2-1.0.2.dist-info/WHEEL
mach2-1.0.2.dist-info/entry_points.txt
mach2-1.0.2.dist-info/licenses/LICENSE
mach2/__init__.py
mach2/__main__.py
mach2/mach2.py
mach2/migrationgraph.py
mach2/solutionset.py
mach2/tree.py
mach2/utils.py
mach2-1.0.2.dist-info/RECORD
