Metadata-Version: 2.1
Name: mach2
Version: 1.0.2
Summary: Migration Analysis of Clonal Histories 2
Keywords: Computational Biology,Bioinformatics,Cancer,Metastasis,Phylogeny,Integer Linear Programming,Combinatorial Optimization
Author-Email: Mrinmoy Saha Roddur <mroddur2@illinois.edu>, Vikram Ramavarapu <vikramr2@illinois.edu>, Abigail Bunkum <abigail.bunkum.21@ucl.ac.uk>, "Ariana Huebner," <ariana.huebner.16@ucl.ac.uk>, Roman Mineyev <mineyev2@illinois.edu>, "Nicholas McGranahan," <nicholas.mcgranahan.10@ucl.ac.uk>, "Simone Zaccaria," <s.zaccaria@ucl.ac.uk>, Mohammed El-Kebir <melkebir@illinois.edu>
Maintainer-Email: Mrinmoy Saha Roddur <mroddur2@illinois.edu>
License: BSD 3-Clause License
Classifier: Programming Language :: Python :: 3.12
Classifier: Operating System :: OS Independent
Classifier: Topic :: Scientific/Engineering :: Bio-Informatics
Project-URL: Homepage, https://github.com/elkebir-group/MACH2
Project-URL: Bug Tracker, https://github.com/elkebir-group/MACH2/issues
Project-URL: Preprint, https://www.biorxiv.org/content/10.1101/2024.11.19.624301v2
Requires-Python: >=3.12
Requires-Dist: pandas
Requires-Dist: networkx
Requires-Dist: jupyterlab
Requires-Dist: graphviz
Provides-Extra: viz
Requires-Dist: mach2-viz; extra == "viz"
